agent_sandbox/__init__.py
agent_sandbox/cli.py
agent_sandbox/config.py
agent_sandbox/main.py
agent_sandbox/runtime.py
agent_sandbox/api/__init__.py
agent_sandbox/api/routes.py
agent_sandbox/api/schemas.py
agent_sandbox/api/websocket.py
agent_sandbox/contracts/__init__.py
agent_sandbox/contracts/agent_output.py
agent_sandbox/contracts/validation.py
agent_sandbox/debugger/__init__.py
agent_sandbox/evaluation/__init__.py
agent_sandbox/evaluation/metrics.py
agent_sandbox/evaluation/problems.py
agent_sandbox/evaluation/runner.py
agent_sandbox/memory/__init__.py
agent_sandbox/orchestrator/__init__.py
agent_sandbox/orchestrator/graph.py
agent_sandbox/orchestrator/state.py
agent_sandbox/orchestrator/nodes/__init__.py
agent_sandbox/orchestrator/nodes/critic.py
agent_sandbox/orchestrator/nodes/executor.py
agent_sandbox/orchestrator/nodes/generator.py
agent_sandbox/orchestrator/nodes/retry.py
agent_sandbox/providers/__init__.py
agent_sandbox/providers/anthropic.py
agent_sandbox/providers/base.py
agent_sandbox/providers/factory.py
agent_sandbox/providers/google.py
agent_sandbox/providers/groq.py
agent_sandbox/providers/ollama.py
agent_sandbox/providers/openai.py
agent_sandbox/providers/openrouter.py
agent_sandbox/quantum/__init__.py
agent_sandbox/quantum/engine.py
agent_sandbox/sandbox/__init__.py
agent_sandbox/sandbox/executor.py
agent_sandbox/sandbox/manager.py
agent_sandbox/sandbox/models.py
agent_sandbox/swarm/__init__.py
agent_sandbox_runtime-1.0.0.dist-info/METADATA
agent_sandbox_runtime-1.0.0.dist-info/WHEEL
agent_sandbox_runtime-1.0.0.dist-info/entry_points.txt
agent_sandbox_runtime-1.0.0.dist-info/licenses/LICENSE
agent_sandbox_runtime-1.0.0.dist-info/RECORD
