Metadata-Version: 2.4
Name: agent-sandbox-runtime
Version: 1.0.0
Summary: Production-grade self-correcting AI agent platform with sandboxed execution
Project-URL: Homepage, https://github.com/ixchio/agent-sandbox-runtime
Project-URL: Documentation, https://github.com/ixchio/agent-sandbox-runtime#readme
Project-URL: Repository, https://github.com/ixchio/agent-sandbox-runtime.git
Project-URL: Issues, https://github.com/ixchio/agent-sandbox-runtime/issues
Project-URL: Changelog, https://github.com/ixchio/agent-sandbox-runtime/releases
Author-email: ixchio <amankumarpandeyin@gmail.com>
Maintainer: Agent Sandbox Runtime Contributors
License: MIT
License-File: LICENSE
Keywords: ai-agents,code-execution,docker,langgraph,llm,sandbox,self-correcting
Classifier: Development Status :: 4 - Beta
Classifier: Intended Audience :: Developers
Classifier: License :: OSI Approved :: MIT License
Classifier: Programming Language :: Python :: 3.11
Classifier: Programming Language :: Python :: 3.12
Classifier: Topic :: Scientific/Engineering :: Artificial Intelligence
Requires-Python: >=3.11
Requires-Dist: aiofiles>=24.1.0
Requires-Dist: anthropic>=0.39.0
Requires-Dist: docker>=7.1.0
Requires-Dist: fastapi>=0.115.0
Requires-Dist: google-generativeai>=0.8.0
Requires-Dist: groq>=0.11.0
Requires-Dist: httpx>=0.27.0
Requires-Dist: langchain>=0.3.0
Requires-Dist: langgraph>=0.2.0
Requires-Dist: openai>=1.50.0
Requires-Dist: pydantic-settings>=2.5.0
Requires-Dist: pydantic>=2.9.0
Requires-Dist: python-dotenv>=1.0.0
Requires-Dist: qdrant-client>=1.12.0
Requires-Dist: redis>=5.2.0
Requires-Dist: rich>=13.9.0
Requires-Dist: structlog>=24.4.0
Requires-Dist: typer>=0.12.0
Requires-Dist: uvicorn[standard]>=0.32.0
Requires-Dist: websockets>=13.0
Provides-Extra: dev
Requires-Dist: mypy>=1.13.0; extra == 'dev'
Requires-Dist: pre-commit>=4.0.0; extra == 'dev'
Requires-Dist: pytest-asyncio>=0.24.0; extra == 'dev'
Requires-Dist: pytest-cov>=5.0.0; extra == 'dev'
Requires-Dist: pytest-docker>=3.1.0; extra == 'dev'
Requires-Dist: pytest>=8.3.0; extra == 'dev'
Requires-Dist: ruff>=0.7.0; extra == 'dev'
